Metadata-Version: 2.1
Name: word-mover-grammar
Version: 0.0.2
Summary: A constituency grammar parser with support of morphology and word embeddings
Home-page: https://github.com/avidale/word-mover-grammar
Author: David Dale
Author-email: dale.david@mail.ru
License: MIT
Platform: UNKNOWN
Classifier: Development Status :: 3 - Alpha
Classifier: Programming Language :: Python :: 3
Classifier: License :: OSI Approved :: MIT License
Classifier: Operating System :: OS Independent
Provides-Extra: rumorph
